Metadata-Version: 2.1
Name: ApiSpbStuRuz
Version: 1.0.6
Summary: Library implementing API schedules of SPbPu
Home-page: https://github.com/DafterT/ApiSpbStuRuz
Author: Dafter
Author-email: DafterPlay@mail.ru
Keywords: python SPbPu
Classifier: Programming Language :: Python :: 3.11
Classifier: License :: OSI Approved :: MIT License
Classifier: Operating System :: OS Independent
Requires-Python: >=3.11
License-File: License.md
